pyreactflow/__init__.py
pyreactflow/ast_node.py
pyreactflow/node.py
pyreactflow/reactflow.py
pyreactflow/test_export.py
pyreactflow-0.2.4.dist-info/licenses/LICENSE
pyreactflow-0.2.4.dist-info/METADATA
pyreactflow-0.2.4.dist-info/WHEEL
pyreactflow-0.2.4.dist-info/top_level.txt
pyreactflow-0.2.4.dist-info/RECORD
