Metadata-Version: 2.4
Name: pyreactflow
Version: 0.2.4
Summary: Python codes to react-flow compatible workflow definitions.
Author-email: "Maton, Inc." <byungkyu@maton.ai>
License: MIT License
Project-URL: Homepage, https://github.com/maton-ai/pyreactflow
Classifier: Development Status :: 3 - Alpha
Classifier: Environment :: Console
Classifier: License :: OSI Approved :: MIT License
Classifier: Programming Language :: Python :: 3
Classifier: Topic :: Software Development :: Code Generators
Classifier: Topic :: Utilities
Requires-Python: >=3.6
License-File: LICENSE
Requires-Dist: astunparse
Requires-Dist: chardet
Dynamic: license-file
